snakemake_storage_plugin_s3/__init__.py
snakemake_storage_plugin_s3-0.3.6.dist-info/LICENSE
snakemake_storage_plugin_s3-0.3.6.dist-info/METADATA
snakemake_storage_plugin_s3-0.3.6.dist-info/WHEEL
snakemake_storage_plugin_s3-0.3.6.dist-info/RECORD
